<skeleton >
  <bones >
    <bone id="0" name="Support" >
      <position x="0.000000" y="0.000000" z="0.000000" />
      <rotation angle="0.000000" >
        <axis x="-0.000000" y="0.000000" z="0.000000" />
      </rotation>
    </bone>
    <bone id="1" name="Arm" >
      <position x="0.000000" y="1.000000" z="0.000000" />
      <rotation angle="2.839412" >
        <axis x="-1.000000" y="0.000000" z="0.000000" />
      </rotation>
    </bone>
  </bones>
  <bonehierarchy >
    <boneparent bone="Arm" parent="Support" />
  </bonehierarchy>
  <animations >
    <animation length="0.4166666666666667" name="Throw" >
      <tracks >
        <track bone="Support" >
          <keyframes >
            <keyframe time="0.0" >
              <translate x="0.000000" y="0.000000" z="0.000000" />
              <rotate angle="0.000000" >
                <axis x="1.000000" y="0.000000" z="0.000000" />
              </rotate>
              <scale x="1.000000" y="1.000000" z="1.000000" />
            </keyframe>
            <keyframe time="0.041666666666666664" >
              <translate x="0.000000" y="0.000000" z="0.000000" />
              <rotate angle="0.000000" >
                <axis x="1.000000" y="0.000000" z="0.000000" />
              </rotate>
              <scale x="1.000000" y="1.000000" z="1.000000" />
            </keyframe>
            <keyframe time="0.08333333333333333" >
              <translate x="0.000000" y="0.000000" z="0.000000" />
              <rotate angle="0.000000" >
                <axis x="1.000000" y="0.000000" z="0.000000" />
              </rotate>
              <scale x="1.000000" y="1.000000" z="1.000000" />
            </keyframe>
            <keyframe time="0.125" >
              <translate x="0.000000" y="0.000000" z="0.000000" />
              <rotate angle="0.000000" >
                <axis x="1.000000" y="0.000000" z="0.000000" />
              </rotate>
              <scale x="1.000000" y="1.000000" z="1.000000" />
            </keyframe>
            <keyframe time="0.16666666666666666" >
              <translate x="0.000000" y="0.000000" z="0.000000" />
              <rotate angle="0.000000" >
                <axis x="1.000000" y="0.000000" z="0.000000" />
              </rotate>
              <scale x="1.000000" y="1.000000" z="1.000000" />
            </keyframe>
            <keyframe time="0.20833333333333334" >
              <translate x="0.000000" y="0.000000" z="0.000000" />
              <rotate angle="0.000000" >
                <axis x="1.000000" y="0.000000" z="0.000000" />
              </rotate>
              <scale x="1.000000" y="1.000000" z="1.000000" />
            </keyframe>
            <keyframe time="0.25" >
              <translate x="0.000000" y="0.000000" z="0.000000" />
              <rotate angle="0.000000" >
                <axis x="1.000000" y="0.000000" z="0.000000" />
              </rotate>
              <scale x="1.000000" y="1.000000" z="1.000000" />
            </keyframe>
            <keyframe time="0.2916666666666667" >
              <translate x="0.000000" y="0.000000" z="0.000000" />
              <rotate angle="0.000000" >
                <axis x="1.000000" y="0.000000" z="0.000000" />
              </rotate>
              <scale x="1.000000" y="1.000000" z="1.000000" />
            </keyframe>
            <keyframe time="0.3333333333333333" >
              <translate x="0.000000" y="0.000000" z="0.000000" />
              <rotate angle="0.000000" >
                <axis x="1.000000" y="0.000000" z="0.000000" />
              </rotate>
              <scale x="1.000000" y="1.000000" z="1.000000" />
            </keyframe>
            <keyframe time="0.375" >
              <translate x="0.000000" y="0.000000" z="0.000000" />
              <rotate angle="0.000000" >
                <axis x="1.000000" y="0.000000" z="0.000000" />
              </rotate>
              <scale x="1.000000" y="1.000000" z="1.000000" />
            </keyframe>
            <keyframe time="0.4166666666666667" >
              <translate x="0.000000" y="0.000000" z="0.000000" />
              <rotate angle="0.000000" >
                <axis x="1.000000" y="0.000000" z="0.000000" />
              </rotate>
              <scale x="1.000000" y="1.000000" z="1.000000" />
            </keyframe>
          </keyframes>
        </track>
        <track bone="Arm" >
          <keyframes >
            <keyframe time="0.0" >
              <translate x="0.000000" y="0.000000" z="0.000000" />
              <rotate angle="0.000000" >
                <axis x="1.000000" y="0.000000" z="0.000000" />
              </rotate>
              <scale x="1.000000" y="1.000000" z="1.000000" />
            </keyframe>
            <keyframe time="0.041666666666666664" >
              <translate x="0.000000" y="0.000000" z="0.000000" />
              <rotate angle="0.196369" >
                <axis x="0.999998" y="0.000000" z="0.000000" />
              </rotate>
              <scale x="1.000000" y="1.000000" z="1.000000" />
            </keyframe>
            <keyframe time="0.08333333333333333" >
              <translate x="0.000000" y="0.000000" z="0.000000" />
              <rotate angle="0.676671" >
                <axis x="1.000001" y="0.000000" z="0.000000" />
              </rotate>
              <scale x="1.000000" y="1.000000" z="1.000000" />
            </keyframe>
            <keyframe time="0.125" >
              <translate x="0.000000" y="0.000000" z="0.000000" />
              <rotate angle="1.085675" >
                <axis x="1.000000" y="0.000000" z="0.000000" />
              </rotate>
              <scale x="1.000000" y="1.000000" z="1.000000" />
            </keyframe>
            <keyframe time="0.16666666666666666" >
              <translate x="0.000000" y="0.000000" z="0.000000" />
              <rotate angle="1.221452" >
                <axis x="1.000000" y="0.000000" z="0.000000" />
              </rotate>
              <scale x="1.000000" y="1.000000" z="1.000000" />
            </keyframe>
            <keyframe time="0.20833333333333334" >
              <translate x="0.000000" y="0.000000" z="0.000000" />
              <rotate angle="1.221452" >
                <axis x="1.000000" y="0.000000" z="0.000000" />
              </rotate>
              <scale x="1.000000" y="1.000000" z="1.000000" />
            </keyframe>
            <keyframe time="0.25" >
              <translate x="0.000000" y="0.000000" z="0.000000" />
              <rotate angle="1.221452" >
                <axis x="1.000000" y="0.000000" z="0.000000" />
              </rotate>
              <scale x="1.000000" y="1.000000" z="1.000000" />
            </keyframe>
            <keyframe time="0.2916666666666667" >
              <translate x="0.000000" y="0.000000" z="0.000000" />
              <rotate angle="1.221452" >
                <axis x="1.000000" y="0.000000" z="0.000000" />
              </rotate>
              <scale x="1.000000" y="1.000000" z="1.000000" />
            </keyframe>
            <keyframe time="0.3333333333333333" >
              <translate x="0.000000" y="0.000000" z="0.000000" />
              <rotate angle="1.221452" >
                <axis x="1.000000" y="0.000000" z="0.000000" />
              </rotate>
              <scale x="1.000000" y="1.000000" z="1.000000" />
            </keyframe>
            <keyframe time="0.375" >
              <translate x="0.000000" y="0.000000" z="0.000000" />
              <rotate angle="0.685379" >
                <axis x="1.000000" y="0.000000" z="0.000000" />
              </rotate>
              <scale x="1.000000" y="1.000000" z="1.000000" />
            </keyframe>
            <keyframe time="0.4166666666666667" >
              <translate x="0.000000" y="0.000000" z="0.000000" />
              <rotate angle="0.000000" >
                <axis x="1.000000" y="0.000000" z="0.000000" />
              </rotate>
              <scale x="1.000000" y="1.000000" z="1.000000" />
            </keyframe>
          </keyframes>
        </track>
      </tracks>
    </animation>
  </animations>
</skeleton>